[
 {
  "name": "Retro Loading Bar",
  "author": "Tawsif Torabi",
  "file": "retro_loading_bar.html"
 },
 {
  "name": "Class TimeTable",
  "author": "dia2git",
  "file": "class_timetable.html"
 },
 {
  "name": "Youtube Thumbnail Grabber",
  "author": "Tawsif Torabi",
  "file": "youtube_thumbnail_grabber.html"
 },
 {
  "name": "Employee List",
  "author": "irfan7o",
  "file": "employe_list.html"
 }, 
 {
  "name": "A List of Table Tags",
  "author": "Hillary Nyakundi",
  "file": "All_Table_Tags.html"
 }, 
 {
  "name": "Multiple Elements in Table",
  "author": "w3Schools",
  "file": "Elements_inside_Table.html"
 },
 {
  "name": "Table Cell Padding",
  "author": "w3Schools",
  "file": "table_cellpadding.html"
 },
 {
  "name": "Flexbox Webpage",
  "author": "w3Schools",
  "file": "Flexbox.html"
 },
 {
  "name": "Countdown Timer",
  "author": "Tawsif Torabi",
  "file": "CountdownTimer.html"
 },  
 {
  "name": "Datetime Input",
  "author": "w3Schools",
  "file": "datetime.html"
 }, 
 {
  "name": "Invoice Table",
  "author": "Adam Wood",
  "file": "Invoice_Table.html"
 },
 {
  "name": "CSS Table Design",
  "author": "Tawsif Torabi",
  "file": "CSSTableDesign.html"
 },
 {
  "name": "Meeting Agenda HTML",
  "author": "Tawsif Torabi",
  "file": "meeting_agenda.html"
 }
 
 {
  "name": "Geolocation",
  "author": "Tawsif Torabi",
  "file": "Geolocation.html"
 }
]
